permutable_nlp_model_inference/__init__.py
permutable_nlp_model_inference/inference.py
permutable_nlp_model_inference-0.1.0.dist-info/METADATA
permutable_nlp_model_inference-0.1.0.dist-info/WHEEL
permutable_nlp_model_inference-0.1.0.dist-info/top_level.txt
permutable_nlp_model_inference-0.1.0.dist-info/RECORD
