Metadata-Version: 2.1
Name: permutable-nlp-model-inference
Version: 0.1.0
Summary: A package for local inference of permutable nlp models
Home-page: https://github.com/shuds13/pyexample
Author: Joshua Ellis
Author-email: joshua@permutable.ai
Classifier: Programming Language :: Python :: 3.8
Requires-Dist: transformers (==3.0.2)
Requires-Dist: torch (==1.12.1)
Requires-Dist: pandas (==1.3.4)
